timedelay/__init__.py
timedelay/estimator.py
timedelay/tdmodel.py
timedelay/timedelay.py
timedelay-0.0.0.dist-info/LICENSE
timedelay-0.0.0.dist-info/METADATA
timedelay-0.0.0.dist-info/WHEEL
timedelay-0.0.0.dist-info/top_level.txt
timedelay-0.0.0.dist-info/RECORD
