Metadata-Version: 2.1
Name: timedelay
Version: 0.0.0
Summary: UNKNOWN
Home-page: UNKNOWN
Author: UNKNOWN
Author-email: UNKNOWN
License: GNU
Platform: UNKNOWN
Requires-Dist: numpy (>=1.10)
Requires-Dist: astropy (>=1.0)
Requires-Dist: seaborn
Requires-Dist: tqdm
